Metadata-Version: 2.1
Name: mcprotection-dashboard
Version: 1.0
Summary: A simple library used in the mcprotection dashboard
Author: seuskaszeba
Author-email: mcp@xyz.com
License: MIT
